mirge/__init__.py
mirge/__main__.py
mirge/classes/__init__.py
mirge/classes/exportHTML.py
mirge/classes/readCluster.py
mirge/classes/readPrecusor.py
mirge/forgi/__init__.py
mirge/forgi/graph/__init__.py
mirge/forgi/graph/bulge_graph.py
mirge/forgi/threedee/__init__.py
mirge/forgi/threedee/utilities/__init__.py
mirge/forgi/threedee/utilities/cytvec.py
mirge/forgi/threedee/utilities/mcannotate.py
mirge/forgi/threedee/utilities/vector.py
mirge/forgi/utilities/__init__.py
mirge/forgi/utilities/debug.py
mirge/forgi/utilities/stuff.py
mirge/libs/__init__.py
mirge/libs/bamFmt.py
mirge/libs/digest.py
mirge/libs/digestEC.py
mirge/libs/generate_featureFiles.py
mirge/libs/kmc
mirge/libs/kmc_dump
mirge/libs/manifoldAlign.py
mirge/libs/miREC_fq
mirge/libs/miRgeEssential.py
mirge/libs/mirge2_tRF_a2i.py
mirge/libs/novel_mir.py
mirge/libs/parse.py
mirge/libs/preprocess_featureFiles.py
mirge/libs/processSam.py
mirge/libs/screen_precusor_candidates.py
mirge/libs/summary.py
mirge/libs/write_novel_report.py
mirge/models/__init__.py
mirge/models/human_svc_model.pkl
mirge/models/mouse_svc_model.pkl
mirge/models/others_svc_model.pkl
mirge/models/total_features_namelist.txt
mirge/rScripts/A-to-I_plot.R
mirge/rScripts/__init__.py
mirge/rScripts/difxp_DESeq.R
mirge3-0.1.4.dist-info/LICENSE
mirge3-0.1.4.dist-info/METADATA
mirge3-0.1.4.dist-info/WHEEL
mirge3-0.1.4.dist-info/entry_points.txt
mirge3-0.1.4.dist-info/top_level.txt
mirge3-0.1.4.dist-info/RECORD
