Metadata-Version: 2.1
Name: mirge3
Version: 0.1.4
Summary: Comprehensive analysis of small RNA sequencing Data
Home-page: https://github.com/mhalushka/miRge3.0/
Author: Arun Patil and Marc Halushka
Author-email: mhalush1@jhmi.edu
License: MIT
Keywords: miRge,small RNA analysis,NGS,bioinformatics tools,GUI
Classifier: Development Status :: 1 - Planning
Classifier: Environment :: Console
Classifier: Intended Audience :: Science/Research
Classifier: License :: OSI Approved :: MIT License
Classifier: Natural Language :: English
Classifier: Programming Language :: Python :: 3.8
Classifier: Topic :: Scientific/Engineering :: Bio-Informatics
Requires-Python: >=3.7
License-File: LICENSE
Requires-Dist: biopython (>=1.78)
Requires-Dist: cutadapt
Requires-Dist: future (>=0.18.2)
Requires-Dist: joblib (>=0.15.1)
Requires-Dist: matplotlib (>=3.2.1)
Requires-Dist: pandas
Requires-Dist: reportlab (>=3.5.42)
Requires-Dist: scikit-learn
Requires-Dist: scipy (>=1.4.1)
